ucall/__init__.py
ucall/_server.py
ucall/cli.py
ucall/client.py
ucall/rich_posix.py
ucall/rich_uring.py
ucall/Release/base64.lib
ucall/Release/mbedcrypto.lib
ucall/Release/mbedtls.lib
ucall/Release/mbedx509.lib
ucall/Release/posix.exp
ucall/Release/posix.lib
ucall/Release/posix.pyd
ucall/Release/simdjson.lib
ucall/Release/ucall_server_posix.lib
ucall-0.5.4.dist-info/LICENSE
ucall-0.5.4.dist-info/METADATA
ucall-0.5.4.dist-info/WHEEL
ucall-0.5.4.dist-info/entry_points.txt
ucall-0.5.4.dist-info/top_level.txt
ucall-0.5.4.dist-info/RECORD
