Metadata-Version: 2.1
Name: ucall
Version: 0.5.4
Summary: Up to 100x Faster FastAPI. JSON-RPC with io_uring, SIMD-acceleration, and pure CPython bindings
Home-page: https://github.com/unum-cloud/ucall
Author: Ash Vardanian
Author-email: info@unum.cloud
License: Apache-2.0
Classifier: Development Status :: 5 - Production/Stable
Classifier: Natural Language :: English
Classifier: Intended Audience :: Developers
Classifier: Intended Audience :: Information Technology
Classifier: License :: OSI Approved :: Apache Software License
Classifier: Programming Language :: Python :: 3 :: Only
Classifier: Programming Language :: Python :: Implementation :: CPython
Classifier: Programming Language :: C
Classifier: Operating System :: Unix
Classifier: Operating System :: POSIX
Classifier: Operating System :: POSIX :: Linux
Classifier: Operating System :: MacOS
Classifier: Programming Language :: C
Classifier: Programming Language :: C++
Classifier: Programming Language :: Python :: Implementation :: CPython
Classifier: Programming Language :: Python :: 3 :: Only
Classifier: Programming Language :: Python :: 3.9
Classifier: Programming Language :: Python :: 3.10
Classifier: Programming Language :: Python :: 3.11
Classifier: Programming Language :: Python :: 3.12
Classifier: Topic :: Communications :: File Sharing
Classifier: Topic :: Internet :: WWW/HTTP
Classifier: Topic :: System :: Networking
Requires-Python: >=3.9
License-File: LICENSE
Requires-Dist: numpy
Requires-Dist: pillow
